odftemplator.py
PythonODFTemplator-1.1.1.dist-info/LICENSE
PythonODFTemplator-1.1.1.dist-info/METADATA
PythonODFTemplator-1.1.1.dist-info/WHEEL
PythonODFTemplator-1.1.1.dist-info/top_level.txt
PythonODFTemplator-1.1.1.dist-info/RECORD
