Metadata-Version: 2.1
Name: PythonODFTemplator
Version: 1.1.1
Summary: ODF templating library for python.
Home-page: https://github.com/marvelph/PythonODFTemplator
Author: Kenji Nishishiro
Author-email: marvel@programmershigh.org
License: MIT
Platform: any
Classifier: Development Status :: 5 - Production/Stable
Classifier: Intended Audience :: Developers
Classifier: License :: OSI Approved :: MIT License
Classifier: Operating System :: POSIX :: Linux
Classifier: Operating System :: MacOS :: MacOS X
Classifier: Programming Language :: Python :: 3
Classifier: Programming Language :: Python :: 3.5
Requires-Python: >=3.5
License-File: LICENSE
Requires-Dist: Jinja2
Requires-Dist: pylokit
